siriusmail/__init__.py
siriusmail/parser.py
siriusmail/rtf_extractor.py
siriusmail-0.0.1.dist-info/LICENSE
siriusmail-0.0.1.dist-info/METADATA
siriusmail-0.0.1.dist-info/WHEEL
siriusmail-0.0.1.dist-info/top_level.txt
siriusmail-0.0.1.dist-info/RECORD
