Metadata-Version: 2.1
Name: siriusmail
Version: 0.0.1
Summary: All those emails
Home-page: https://github.com/pypa/siriusmail
Author: lonecello
Author-email: heimercryo@gmail.com
License: UNKNOWN
Project-URL: Bug Tracker, https://github.com/pypa/siriusmail/issues
Platform: UNKNOWN
Classifier: Programming Language :: Python :: 3
Classifier: License :: OSI Approved :: MIT License
Classifier: Operating System :: OS Independent
Requires-Python: >=3.6
License-File: LICENSE
